{"categories_6809637767543259144.md":"BNuEW6Gm","categories_6809637769959178254.md":"DD04r3gB","categories_6809637772874219534.md":"KelPXbII","categories_6809637773935378440.md":"BDbak8Ig","categories_index.md":"IOrjHkzz","columns_7107151273765371941.md":"B-eux8CV","columns_7187392655192490043.md":"CXwCluDt","columns_index.md":"Bjd-2kSf","index.md":"C9WQzPh4","overview_index.md":"BjnuoBrE","ranking_index.md":"BOV9zytG","recent_index.md":"CDRJyiaS","years_2022.md":"CF992XTl","years_2023.md":"CzUjuVfT","years_2024.md":"idw9qeuW"}
